{
  "逆境绽放之花": {
    "style_info": [
      "./角色/31X/CSkopovskaya/CSkopovskayaDefault_R3_Thumbnail.webp",
      "31X","夏洛塔·斯科波夫斯卡娅",
      "逆境绽放之花",
      ["原皮夏洛", "暗夏洛"],
      "只要SP在0以上就能使用必杀技的DEBUFFER风格",
      "SS",
      "减益者",
      "突",
      "暗"
    ],
    "ActiveSkills": [
      [
        [
          "为你绽放的手榴弹",
          "降低全体敌方的防御力和暗属性防御力\n用暗之子弹射穿手榴弹引发爆炸\nSP0或以上即可使用",
          "13",
          "4"
        ],
        [
          [
            "防御下降",
            "20 ~ 30%",
            {
              "智慧": "2",
              "运气": "1"
            },
            "140",
            "1",
            "敌方回合",
            "全体"
          ],
          [
            "暗防御下降",
            "30 ~ 45%",
            {
              "智慧": "2",
              "运气": "1"
            },
            "140",
            "1",
            "敌方回合",
            "全体"
          ],
          [
            "突",
            "暗",
            "3",
            [0.2,0.2,0.6],
            "1,340 ~ 6,701",
            {
              "力量": "1",
              "灵巧": "1"
            },
            null,
            "140",
            "2.3",
            "全体"
          ]
        ],
        [
          "38",
          "66",
          "78"
        ],
        "13"
      ],
      [
        [
          "慌乱的子弹",
          "进行集中炮击\n并有概率使目标混乱",
          "9",
          null
        ],
        [
          [
            "突",
            null,
            "3",
            null,
            "1,122 ~ 5,610",
            {
              "力量": "1",
              "灵巧": "1"
            },
            null,
            "132",
            "2.25",
            "单体"
          ],
          [
            "混乱",
            "30 ~ 85%概率附加",
            {
              "智慧": "1",
              "运气": "2"
            },
            "132",
            "2",
            "敌方回合",
            "单体"
          ]
        ],
        [
          "14",
          "25",
          "57"
        ]
      ]
      
    ],
    "PassiveSkills": [
        ["闪光", 
        "若回合开始时位于前锋\n则自身的SP+1",
        "1",
        "回复SP",
        "1",
        null,
        null,
        "自身"],
        ["侵蚀", 
        "自身施动加的\n降防效果+25%",
        "3",
        "防御下降技能强化",
        "25%",

        "1",
        "己方回合",
        "自身"]
    ],
    "GrowthAbility": "提升减益型技能效果量",
    "status_growth": {
      "DP": "+70% +200",
      "力量": "+40% +35",
      "体力": "+55% +37",
      "智慧": "+55% +37",
      "灵巧": "+70% +39",
      "精神": "+50% +35",
      "运气": "+60% +39"
    }
  },


  "永恒的思念": {
    "style_info": [
      "./角色/31X/CSkopovskaya/CSkopovskayaVampire_R3_Thumbnail.webp",
      "31X","夏洛塔·斯科波夫斯卡娅",
      "永恒的思念",
      ["雷夏洛"],
      "可降低全体敌人雷属性抗性的DEBUFFER风格",
      "SS",
      "减益者",
      "突",
      "雷"
    ],
    "ActiveSkills": [
      [
        [
          "纯洁之吻",
          "使用结晶之力消除全体敌方的雷属性抗性\n降低其雷属性抗性（永久回合）\n使敌方进入脆弱状态并释放猩红的雷击\nSP0或以上即可使用",
          "15",
          "4"
        ],
        [
          [
            "雷抗性清除",
            null,
            null,
            null,
            "永久",
            null,
            "全体"
          ],
          [
            "雷抗性下降",
            "45 ~ 60%",
            {
              "智慧": "2",
              "运气": "1"
            },
            "141",
            "永久",
            null,
            "全体"
          ],
          [
            "脆弱",
            "35 ~ 50%",
            {
              "智慧": "1",
              "运气": "2"
            },
            "141",
            "1",
            "敌方回合",
            "全体"
          ],
          [
            "突",
            "雷",
            "3",
            [0.3,0.3,0.4],
            "1,446 ~ 7,230",
            {
              "力量": "1",
              "灵巧": "1"
            },
            null,
            "141",
            "2.4",
            "全体"
          ]
        ],
        [
          "43",
          "68",
          "80"
        ]
      ],
      [
        [
          "依存",
          "进行大范围炮击\n并降低敌方雷属性防御力",
          "5",
          null
        ],
        [
          [
            "突",
            null,
            "3",
            null,
            "375 ~ 1,875",
            {
              "力量": "1",
              "灵巧": "1"
            },
            null,
            "120",
            "1",
            "全体"
          ],
          [
            "雷防御下降",
            "30 ~ 45%",
            {
              "智慧": "2",
              "运气": "1"
            },
            "120",
            "1",
            "敌方回合",
            "全体"
          ]
        ],
        [
          "8",
          "22",
          "54"
        ]
      ]
    ],
    "PassiveSkills": [
        ["雷之波动", 
        "全体友方的雷属性技能攻击力\n持续+10%",
        "0",
        "雷攻击上升",
        "10%",

        null,
        null,
        "全体友方"],
        ["闪光", 
        "若回合开始时位于前锋\n则自身的SP+1",
        "1",
        "回复SP",
        "1",
        null,
        null,
        "自身"],
      [
        "雷之压制",
        "若行动开始时位于前锋 & DP在80%以上\n则敌方雷属性防御力-18%",
        "3",
        "雷防御下降",
        "18%",
        "1",
        "己方回合",
        "全体"
      ]
    ],
    "GrowthAbility": "提升减益型技能效果量",
    "status_growth": {
      "DP": "+70% +200",
      "力量": "+40% +35",
      "体力": "+55% +37",
      "智慧": "+55% +37",
      "灵巧": "+70% +39",
      "精神": "+50% +35",
      "运气": "+60% +39"
    }
  },

  "圣洁新娘": {
    "style_info": [
      "./角色/31X/CSkopovskaya/CSkopovskayaBride_R3_Thumbnail.webp",
      "31X","夏洛塔·斯科波夫斯卡娅",
      "圣洁新娘",
      ["婚纱夏洛","花嫁夏洛"],
      "能永续支援自己和我方单体的BUFFER风格",
      "SS",
      "增益者",
      "突",
      "暗"
    ],
    "ActiveSkills": [
      [
        [
          "念人陶醉的圣洁之路",
          "使自身和友方单体进入永恒的誓言状态（永久）\n并提升5点SP\nSP0或以上即可使用",
          "10",
          "1"
        ],
        [
          ["永恒誓言", "不可移除", null ,null, null, null, "一名其他友方"],
          ["回复SP", "5", null, null, null, null, "一名其他友方"],
          ["永恒誓言", "不可移除", null ,null, null, null, "自身"],
          ["回复SP", "5", null, null, null, null, "自身"]
        ],
        [
          "",
          "",
          "60"
        ],
        "1"
      ],
      [
        [
          "宣誓",
          "提升友方单体技能攻击力和暗属性技能攻击力\nSP0或以上即可使用",
          "5",
          null
        ],
        [
          ["暗攻击上升", "65 ~ 80%", {"智慧": "1"}, "232", "1", "次", "一名友方"],
          ["攻击上升", "50 ~ 65%", {"智慧": "1"}, "232", "1", "次", "一名友方"]
        ],
        [
          "10",
          "37",
          "48"
        ]
      ]
    ],
    "PassiveSkills": [
        ["订婚戒指", 
        "若回合开始时位于前锋\n包含自身在内处于永恒的誓言状态的友方SP+1",
        "0",
        "回复SP",
        "1，处于永恒的誓言状态",

        null,
        null,
        "全体友方"],

        ["闪光", 
        "若回合开始时位于前锋\n则自身的SP+1",
        "1",
        "回复SP",
        "1",
        null,
        null,
        "自身"],

        [
          "纯真面纱",
          "回合开始时\n包含自身在内处于永恒的誓言状态的友方DP+15%",
          "3",
          "回复DP",
          "15%，处于永恒的誓言状态",
          null,
          null,
          "全体友方"
        ]
    ],
    "GrowthAbility": "提升技能攻击力上升效果量",
    "status_growth": {
      "DP": "+70% +200",
      "力量": "+55% +37",
      "体力": "+40% +35",
      "智慧": "+70% +39",
      "灵巧": "+55% +37",
      "精神": "+60% +39",
      "运气": "+50% +35"
    }
  }


}